custom_components/__init__.py
custom_components/rtl_433_discoverandsubmit/__init__.py
custom_components/rtl_433_discoverandsubmit/config_flow.py
custom_components/rtl_433_discoverandsubmit/const.py
custom_components/rtl_433_discoverandsubmit/decode.py
custom_components/rtl_433_discoverandsubmit/discovery.py
custom_components/rtl_433_discoverandsubmit/config/device_mappings.json
rtl_433_discoverandsubmit/__init__.py
rtl_433_discoverandsubmit/config.py
rtl_433_discoverandsubmit/modules/__init__.py
rtl_433_discoverandsubmit/modules/cli_interface.py
rtl_433_discoverandsubmit/modules/config_loader.py
rtl_433_discoverandsubmit/modules/device_manager.py
rtl_433_discoverandsubmit/modules/ha_integration.py
rtl_433_discoverandsubmit/modules/mqtt_client.py
rtl_433_discoverandsubmit-0.1.14.dist-info/licenses/LICENSE
rtl_433_discoverandsubmit-0.1.14.dist-info/METADATA
rtl_433_discoverandsubmit-0.1.14.dist-info/WHEEL
rtl_433_discoverandsubmit-0.1.14.dist-info/entry_points.txt
rtl_433_discoverandsubmit-0.1.14.dist-info/top_level.txt
rtl_433_discoverandsubmit-0.1.14.dist-info/RECORD
