Metadata-Version: 2.4
Name: rtl_433_discoverandsubmit
Version: 0.1.14
Summary: A small command line utility to connect to an MQTT server, listen to rtl_433 events and allow a user to generate auto-discovery config for home assistant for the devices they choose
Author: Tom George
Author-email: tom@penberth.com
License: MIT
Keywords: rtl_433 mqtt homeassistant
License-File: LICENSE
Requires-Dist: paho-mqtt
Requires-Dist: windows-curses; platform_system == "Windows"
Dynamic: author
Dynamic: author-email
Dynamic: description
Dynamic: description-content-type
Dynamic: keywords
Dynamic: license
Dynamic: license-file
Dynamic: requires-dist
Dynamic: summary
